<?xml version="1.0" encoding="UTF-8"?>
<osm version="0.6" generator="Overpass API 0.7.55.3 9da5e7ae">
<note>The data included in this document is from www.openstreetmap.org. The data is made available under ODbL.</note>
<meta osm_base="2018-06-16T19:00:02Z"/>

  <node id="3367724750" lat="34.7683280" lon="138.0172335" version="1" timestamp="2015-02-23T09:26:32Z" changeset="29039719" uid="692002" user="下り専門">
    <tag k="bus" v="yes"/>
    <tag k="highway" v="bus_stop"/>
    <tag k="name" v="南一丁目"/>
    <tag k="public_transport" v="platform"/>
    <tag k="source" v="survey"/>
  </node>
  <node id="3367724751" lat="34.7653869" lon="138.0178583" version="1" timestamp="2015-02-23T09:26:32Z" changeset="29039719" uid="692002" user="下り専門">
    <tag k="bus" v="yes"/>
    <tag k="highway" v="bus_stop"/>
    <tag k="name" v="南二丁目"/>
    <tag k="public_transport" v="platform"/>
    <tag k="source" v="survey"/>
  </node>
  <node id="3367724755" lat="34.7712252" lon="138.0153581" version="3" timestamp="2016-10-03T15:32:37Z" changeset="42608305" uid="3688357" user="Kohki Hiraga">
    <tag k="bus" v="yes"/>
    <tag k="highway" v="bus_stop"/>
    <tag k="name" v="栄町"/>
    <tag k="public_transport" v="platform"/>
  </node>
  <node id="3367724756" lat="34.7672851" lon="138.0175451" version="1" timestamp="2015-02-23T09:26:33Z" changeset="29039719" uid="692002" user="下り専門">
    <tag k="bus" v="yes"/>
    <tag k="highway" v="bus_stop"/>
    <tag k="name" v="神代地公民館前"/>
    <tag k="public_transport" v="platform"/>
    <tag k="source" v="survey"/>
  </node>
  <node id="3380975279" lat="34.7641705" lon="138.0210110" version="1" timestamp="2015-03-03T12:04:08Z" changeset="29220921" uid="692002" user="下り専門">
    <tag k="bus" v="yes"/>
    <tag k="highway" v="bus_stop"/>
    <tag k="name" v="東名掛川"/>
    <tag k="name:ja_kana" v="とうめいかけがわ"/>
    <tag k="public_transport" v="platform"/>
    <tag k="source" v="survey"/>
  </node>
  <node id="3380975280" lat="34.7644427" lon="138.0210279" version="1" timestamp="2015-03-03T12:04:08Z" changeset="29220921" uid="692002" user="下り専門">
    <tag k="bus" v="yes"/>
    <tag k="highway" v="bus_stop"/>
    <tag k="name" v="東名掛川"/>
    <tag k="name:ja_kana" v="とうめいかけがわ"/>
    <tag k="public_transport" v="platform"/>
    <tag k="source" v="survey"/>
  </node>
  <node id="4143784580" lat="34.7707181" lon="137.9918000" version="1" timestamp="2016-04-24T01:38:56Z" changeset="38824198" uid="692002" user="下り専門">
    <tag k="bus" v="yes"/>
    <tag k="highway" v="bus_stop"/>
    <tag k="name" v="つくし会館入口"/>
    <tag k="operator" v="掛川市"/>
    <tag k="public_transport" v="platform"/>
  </node>
  <node id="4143785133" lat="34.7692612" lon="137.9986888" version="1" timestamp="2016-04-24T01:39:00Z" changeset="38824198" uid="692002" user="下り専門">
    <tag k="bus" v="yes"/>
    <tag k="highway" v="bus_stop"/>
    <tag k="name" v="市役所"/>
    <tag k="operator" v="掛川市"/>
    <tag k="public_transport" v="platform"/>
  </node>
  <node id="4143785134" lat="34.7693070" lon="137.9961622" version="2" timestamp="2016-04-25T11:20:58Z" changeset="38854164" uid="692002" user="下り専門">
    <tag k="bus" v="yes"/>
    <tag k="highway" v="bus_stop"/>
    <tag k="name" v="新長谷橋南"/>
    <tag k="operator" v="掛川市"/>
    <tag k="public_transport" v="platform"/>
  </node>
  <node id="4143785136" lat="34.7707722" lon="137.9941270" version="1" timestamp="2016-04-24T01:39:00Z" changeset="38824198" uid="692002" user="下り専門">
    <tag k="bus" v="yes"/>
    <tag k="highway" v="bus_stop"/>
    <tag k="name" v="橘町"/>
    <tag k="operator" v="掛川市"/>
    <tag k="public_transport" v="platform"/>
  </node>
  <node id="4143785137" lat="34.7700348" lon="137.9971725" version="2" timestamp="2017-02-11T23:07:54Z" changeset="46008928" uid="3385340" user="Lombroso">
    <tag k="bus" v="yes"/>
    <tag k="highway" v="bus_stop"/>
    <tag k="name" v="生物循環パビリオン前"/>
    <tag k="name:ja" v="生物循環パビリオン前"/>
    <tag k="name:ja-Hira" v="せいぶつじゅんかんぱびりおんまえ"/>
    <tag k="name:ja-Latn" v="Sēbutsu Junkan Pabirion Mae"/>
    <tag k="operator" v="掛川市"/>
    <tag k="public_transport" v="platform"/>
  </node>
  <node id="4143837389" lat="34.7606204" lon="138.0264051" version="1" timestamp="2016-04-24T03:10:04Z" changeset="38824922" uid="692002" user="下り専門">
    <tag k="bus" v="yes"/>
    <tag k="highway" v="bus_stop"/>
    <tag k="name" v="希望の丘"/>
    <tag k="operator" v="掛川市"/>
    <tag k="public_transport" v="platform"/>
  </node>
  <node id="4153387718" lat="34.7711979" lon="138.0027300" version="1" timestamp="2016-04-28T12:17:04Z" changeset="38948923" uid="692002" user="下り専門">
    <tag k="bus" v="yes"/>
    <tag k="highway" v="bus_stop"/>
    <tag k="name" v="中央三丁目東"/>
    <tag k="operator" v="掛川市"/>
    <tag k="public_transport" v="platform"/>
  </node>
  <node id="4153387719" lat="34.7712750" lon="138.0029205" version="1" timestamp="2016-04-28T12:17:04Z" changeset="38948923" uid="692002" user="下り専門">
    <tag k="bus" v="yes"/>
    <tag k="highway" v="bus_stop"/>
    <tag k="name" v="中央三丁目東"/>
    <tag k="operator" v="掛川市"/>
    <tag k="public_transport" v="platform"/>
  </node>
  <node id="4153387720" lat="34.7714478" lon="138.0003889" version="1" timestamp="2016-04-28T12:17:04Z" changeset="38948923" uid="692002" user="下り専門">
    <tag k="bus" v="yes"/>
    <tag k="highway" v="bus_stop"/>
    <tag k="name" v="中央三丁目西"/>
    <tag k="operator" v="掛川市"/>
    <tag k="public_transport" v="platform"/>
  </node>
  <node id="4155447720" lat="34.7681830" lon="138.0194567" version="1" timestamp="2016-04-29T11:08:44Z" changeset="38978586" uid="692002" user="下り専門">
    <tag k="bus" v="yes"/>
    <tag k="highway" v="bus_stop"/>
    <tag k="name" v="上張"/>
    <tag k="public_transport" v="platform"/>
  </node>
  <node id="4155447721" lat="34.7680652" lon="138.0257577" version="1" timestamp="2016-04-29T11:08:45Z" changeset="38978586" uid="692002" user="下り専門">
    <tag k="bus" v="yes"/>
    <tag k="highway" v="bus_stop"/>
    <tag k="name" v="掛川税務署前"/>
    <tag k="operator" v="掛川市"/>
    <tag k="public_transport" v="platform"/>
  </node>
  <node id="4155447722" lat="34.7680783" lon="138.0212350" version="1" timestamp="2016-04-29T11:08:45Z" changeset="38978586" uid="692002" user="下り専門">
    <tag k="bus" v="yes"/>
    <tag k="highway" v="bus_stop"/>
    <tag k="name" v="緑ヶ丘一丁目"/>
    <tag k="operator" v="掛川市"/>
    <tag k="public_transport" v="platform"/>
  </node>
  <node id="4155447723" lat="34.7681912" lon="138.0239865" version="1" timestamp="2016-04-29T11:08:45Z" changeset="38978586" uid="692002" user="下り専門">
    <tag k="bus" v="yes"/>
    <tag k="highway" v="bus_stop"/>
    <tag k="name" v="緑ヶ丘二丁目"/>
    <tag k="operator" v="掛川市"/>
    <tag k="public_transport" v="platform"/>
  </node>
  <node id="4225036663" lat="34.7684895" lon="138.0151568" version="1" timestamp="2016-06-04T06:33:47Z" changeset="39792261" uid="3688357" user="Kohki Hiraga">
    <tag k="highway" v="bus_stop"/>
    <tag k="name" v="新幹線口"/>
  </node>
  <node id="4247636454" lat="34.7649216" lon="138.0238832" version="1" timestamp="2016-06-17T00:09:15Z" changeset="40080629" uid="631141" user="Ryo-a">
    <tag k="bench" v="yes"/>
    <tag k="bin" v="yes"/>
    <tag k="bus" v="yes"/>
    <tag k="covered" v="yes"/>
    <tag k="highway" v="bus_stop"/>
    <tag k="name" v="東名掛川"/>
    <tag k="operator" v="JR東海バス"/>
    <tag k="public_transport" v="platform"/>
    <tag k="shelter" v="yes"/>
    <tag k="source" v="GSImaps/ort;survey"/>
  </node>
  <node id="4247636455" lat="34.7653415" lon="138.0227017" version="1" timestamp="2016-06-17T00:09:15Z" changeset="40080629" uid="631141" user="Ryo-a">
    <tag k="bench" v="yes"/>
    <tag k="bin" v="yes"/>
    <tag k="bus" v="yes"/>
    <tag k="covered" v="yes"/>
    <tag k="highway" v="bus_stop"/>
    <tag k="name" v="東名掛川"/>
    <tag k="operator" v="JR東海バス"/>
    <tag k="public_transport" v="platform"/>
    <tag k="shelter" v="yes"/>
  </node>
  <node id="4467201315" lat="34.7700829" lon="138.0144299" version="1" timestamp="2016-10-28T02:24:57Z" changeset="43234449" uid="3888199" user="t-yutaka">
    <tag k="highway" v="bus_stop"/>
    <tag k="name" v="掛川駅北口３番乗り場"/>
  </node>
  <node id="4467201316" lat="34.7699902" lon="138.0144309" version="1" timestamp="2016-10-28T02:24:57Z" changeset="43234449" uid="3888199" user="t-yutaka">
    <tag k="highway" v="bus_stop"/>
    <tag k="name" v="掛川駅北口４番乗り場"/>
  </node>
  <node id="4467201333" lat="34.7703567" lon="138.0148300" version="1" timestamp="2016-10-28T02:24:57Z" changeset="43234449" uid="3888199" user="t-yutaka">
    <tag k="highway" v="bus_stop"/>
    <tag k="name" v="掛川駅前７番乗り場"/>
  </node>
  <node id="4467201334" lat="34.7703514" lon="138.0146852" version="1" timestamp="2016-10-28T02:24:58Z" changeset="43234449" uid="3888199" user="t-yutaka">
    <tag k="highway" v="bus_stop"/>
    <tag k="name" v="掛川駅前６番乗り場"/>
  </node>
  <node id="4467201335" lat="34.7703420" lon="138.0144507" version="1" timestamp="2016-10-28T02:24:58Z" changeset="43234449" uid="3888199" user="t-yutaka">
    <tag k="highway" v="bus_stop"/>
    <tag k="name" v="掛川駅前５番乗り場"/>
  </node>
  <node id="4948803940" lat="34.7547658" lon="138.0282180" version="1" timestamp="2017-07-03T12:23:02Z" changeset="50007651" uid="692002" user="下り専門">
    <tag k="highway" v="bus_stop"/>
    <tag k="name" v="青田"/>
    <tag k="name:ja-Hira" v="あおだ"/>
    <tag k="operator" v="しずてつジャストライン"/>
    <tag k="public_transport" v="platform"/>
  </node>

</osm>
